train_test_sim/__init__.py
train_test_sim/train_test_sim.py
train_test_sim-0.1.1.dist-info/METADATA
train_test_sim-0.1.1.dist-info/WHEEL
train_test_sim-0.1.1.dist-info/top_level.txt
train_test_sim-0.1.1.dist-info/RECORD
