Metadata-Version: 2.1
Name: train-test-sim
Version: 0.1.1
Summary: Library to create simulation to find out what train test ratio is ideal
Author: Marcel Tino
Author-email: <marceltino92@gmail.com>
Keywords: train test,simulation
Requires-Dist: pandas
Requires-Dist: numpy
Requires-Dist: scikit-learn
